pytac/__init__.py
pytac/__main__.py
pytac/_version.py
pytac/cothread_cs.py
pytac/cs.py
pytac/data_source.py
pytac/device.py
pytac/element.py
pytac/exceptions.py
pytac/lattice.py
pytac/load_csv.py
pytac/units.py
pytac/utils.py
pytac/data/48/elements.csv
pytac/data/48/epics_devices.csv
pytac/data/48/families.csv
pytac/data/48/simple_devices.csv
pytac/data/48/uc_pchip_data.csv
pytac/data/48/uc_poly_data.csv
pytac/data/48/unitconv.csv
pytac/data/DIAD/elements.csv
pytac/data/DIAD/epics_devices.csv
pytac/data/DIAD/families.csv
pytac/data/DIAD/simple_devices.csv
pytac/data/DIAD/uc_pchip_data.csv
pytac/data/DIAD/uc_poly_data.csv
pytac/data/DIAD/unitconv.csv
pytac/data/DIADSP/elements.csv
pytac/data/DIADSP/epics_devices.csv
pytac/data/DIADSP/families.csv
pytac/data/DIADSP/simple_devices.csv
pytac/data/DIADSP/uc_pchip_data.csv
pytac/data/DIADSP/uc_poly_data.csv
pytac/data/DIADSP/unitconv.csv
pytac/data/DIADTHz/elements.csv
pytac/data/DIADTHz/epics_devices.csv
pytac/data/DIADTHz/families.csv
pytac/data/DIADTHz/simple_devices.csv
pytac/data/DIADTHz/uc_pchip_data.csv
pytac/data/DIADTHz/uc_poly_data.csv
pytac/data/DIADTHz/unitconv.csv
pytac/data/I04/elements.csv
pytac/data/I04/epics_devices.csv
pytac/data/I04/families.csv
pytac/data/I04/simple_devices.csv
pytac/data/I04/uc_pchip_data.csv
pytac/data/I04/uc_poly_data.csv
pytac/data/I04/unitconv.csv
pytac/data/I04SP/elements.csv
pytac/data/I04SP/epics_devices.csv
pytac/data/I04SP/families.csv
pytac/data/I04SP/simple_devices.csv
pytac/data/I04SP/uc_pchip_data.csv
pytac/data/I04SP/uc_poly_data.csv
pytac/data/I04SP/unitconv.csv
pytac/data/I04THz/elements.csv
pytac/data/I04THz/epics_devices.csv
pytac/data/I04THz/families.csv
pytac/data/I04THz/simple_devices.csv
pytac/data/I04THz/uc_pchip_data.csv
pytac/data/I04THz/uc_poly_data.csv
pytac/data/I04THz/unitconv.csv
pytac/data/utils/load_mml.m
pytac/data/utils/load_unitconv.m
pytac-1.0.0.dist-info/licenses/LICENSE
pytac-1.0.0.dist-info/METADATA
pytac-1.0.0.dist-info/WHEEL
pytac-1.0.0.dist-info/entry_points.txt
pytac-1.0.0.dist-info/top_level.txt
pytac-1.0.0.dist-info/RECORD
